MANIFEST.in
README.rst
setup.py
statsdly.py
statsdly.egg-info/PKG-INFO
statsdly.egg-info/SOURCES.txt
statsdly.egg-info/dependency_links.txt
statsdly.egg-info/entry_points.txt
statsdly.egg-info/not-zip-safe
statsdly.egg-info/top_level.txt